LICENSE
MANIFEST.in
README.rst
ghmiles.py
setup.py
ghmiles.egg-info/PKG-INFO
ghmiles.egg-info/SOURCES.txt
ghmiles.egg-info/dependency_links.txt
ghmiles.egg-info/requires.txt
ghmiles.egg-info/top_level.txt