Metadata-Version: 1.0
Name: ghmiles
Version: 0.1
Summary: GitHub Milestones
Home-page: https://github.com/bartdag/ghmiles
Author: Barthelemy Dagenais
Author-email: barthe@users.sourceforge.net
License: BSD License
Platform: UNKNOWN
